agent_runtimes/__init__.py
agent_runtimes/__main__.py
agent_runtimes/__version__.py
agent_runtimes/_version.py
agent_runtimes/app.py
agent_runtimes/main.py
agent_runtimes/adapters/__init__.py
agent_runtimes/adapters/base.py
agent_runtimes/adapters/jupyter_ai_adapter.py
agent_runtimes/adapters/langchain_adapter.py
agent_runtimes/adapters/pydantic_ai_adapter.py
agent_runtimes/agents/__init__.py
agent_runtimes/agents/demo/__init__.py
agent_runtimes/agents/demo/demo_agent.py
agent_runtimes/agents/examples/__init__.py
agent_runtimes/agents/examples/agentic_chat.py
agent_runtimes/agents/examples/agentic_generative_ui.py
agent_runtimes/agents/examples/backend_tool_rendering.py
agent_runtimes/agents/examples/haiku_generative_ui.py
agent_runtimes/agents/examples/human_in_the_loop.py
agent_runtimes/agents/examples/shared_state.py
agent_runtimes/agents/examples/tool_based_generative_ui.py
agent_runtimes/agents/restaurant_finder/__init__.py
agent_runtimes/agents/restaurant_finder/a2ui_examples.py
agent_runtimes/agents/restaurant_finder/a2ui_schema.py
agent_runtimes/agents/restaurant_finder/agent.py
agent_runtimes/agents/restaurant_finder/restaurant_data.py
agent_runtimes/config/__init__.py
agent_runtimes/config/frontend_config.py
agent_runtimes/context/__init__.py
agent_runtimes/context/optimizer.py
agent_runtimes/context/snapshot.py
agent_runtimes/context/usage.py
agent_runtimes/integrations/__init__.py
agent_runtimes/integrations/codemode.py
agent_runtimes/jupyter/__init__.py
agent_runtimes/jupyter/__main__.py
agent_runtimes/jupyter/agent.py
agent_runtimes/jupyter/config.py
agent_runtimes/jupyter/serverapplication.py
agent_runtimes/jupyter/handlers/__init__.py
agent_runtimes/jupyter/handlers/base.py
agent_runtimes/jupyter/handlers/chat_handler.py
agent_runtimes/jupyter/handlers/config_handler.py
agent_runtimes/jupyter/handlers/configure_handler.py
agent_runtimes/jupyter/handlers/index_handler.py
agent_runtimes/jupyter/handlers/login_handler.py
agent_runtimes-0.0.7.dist-info/METADATA
agent_runtimes-0.0.7.dist-info/WHEEL
agent_runtimes-0.0.7.dist-info/entry_points.txt
agent_runtimes-0.0.7.dist-info/licenses/LICENSE
agent_runtimes-0.0.7.dist-info/RECORD
