Metadata-Version: 2.1
Name: agent_runtimes
Version: 0.0.7
Summary: Agent Runtimes
Project-URL: Homepage, https://github.com/datalayer/agent-runtimes
Project-URL: Documentation, https://agent-runtimes.datalayer.tech
Project-URL: Repository, https://github.com/datalayer/agent-runtimes
Project-URL: Issues, https://github.com/datalayer/agent-runtimes/issues
Project-URL: Changelog, https://github.com/datalayer/agent-runtimes/blob/main/CHANGELOG.md
License: BSD-3-Clause
License-File: LICENSE
Classifier: Framework :: Jupyter
Classifier: Intended Audience :: Developers
Classifier: Intended Audience :: Science/Research
Classifier: Intended Audience :: System Administrators
Classifier: Programming Language :: Python
Classifier: Programming Language :: Python :: 3
Classifier: Programming Language :: Python :: 3.10
Classifier: Programming Language :: Python :: 3.11
Classifier: Programming Language :: Python :: 3.12
Classifier: Programming Language :: Python :: 3.13
Requires-Python: >=3.10
Requires-Dist: a2a-sdk[all]
Requires-Dist: ag-ui-protocol
Requires-Dist: agent-client-protocol
Requires-Dist: agent-skills
Requires-Dist: anthropic
Requires-Dist: code-sandboxes
Requires-Dist: datalayer-core
Requires-Dist: fasta2a
Requires-Dist: jupyter-server<3,>=2.10
Requires-Dist: mcp-codemode
Requires-Dist: mcp-ui-server
Requires-Dist: pydantic-ai-slim[anthropic,bedrock,dbos,google,mcp,openai]
Requires-Dist: pydantic-graph
Requires-Dist: pydantic-settings
Requires-Dist: pydantic[email]
Requires-Dist: typer
Provides-Extra: docs
Requires-Dist: click>=8.3.1; extra == 'docs'
Requires-Dist: npdoc-to-md; extra == 'docs'
Requires-Dist: pydoc-markdown>=4.0; extra == 'docs'
Provides-Extra: examples
Requires-Dist: fastapi; extra == 'examples'
Requires-Dist: pydantic; extra == 'examples'
Requires-Dist: scikit-learn; extra == 'examples'
Requires-Dist: streamlit; extra == 'examples'
Requires-Dist: torch; extra == 'examples'
Requires-Dist: uvicorn; extra == 'examples'
Provides-Extra: test
Requires-Dist: coverage; extra == 'test'
Requires-Dist: mypy; extra == 'test'
Requires-Dist: pytest; extra == 'test'
Requires-Dist: pytest-asyncio; extra == 'test'
Requires-Dist: pytest-cov; extra == 'test'
Requires-Dist: pytest-jupyter; extra == 'test'
Requires-Dist: pytest-tornasync; extra == 'test'
Requires-Dist: python-dotenv; extra == 'test'
Requires-Dist: types-requests; extra == 'test'
Requires-Dist: typing-extensions; extra == 'test'
